Metadata-Version: 1.0
Name: make-corpus
Version: 0.0.2
Summary: maiking corpus from a sentence
Home-page: https://github.com/kennethreitz/samplemod
Author: Takaaki Miwa
Author-email: cryptofran1@gmail.com
License: MIT
Platform: UNKNOWN
